{
    "name": "Close Range",
    "description": "Your projectiles deal less damage and you take more damage from projectiles.",
    "type": "origins:multiple",
    "taken": {
        "type": "origins:modify_damage_taken",
        "damage_condition": {
            "type": "origins:projectile"
        },
        "modifier": {
            "operation": "multiply_base",
            "value": 1,
            "name": "Close Range Bonus"
        }
    },
    "dealt": {
        "type": "origins:modify_projectile_damage",
        "modifier": {
            "operation": "multiply_base",
            "value": -0.2,
            "name": "Close Range Penalty"
        }
    }
}