{
  "dependencies": [
    "complex_curiosities_2"
  ],
  "tasks": {
    "submit_lube_bearing": {
      "type": "heracles:item",
      "item": "kubejs:lubricated_bearing",
      "amount": 16,
      "collection": "MANUAL"
    }
  },
  "rewards": {},
  "display": {
    "subtitle": {
      "text": ""
    },
    "description": [
      "## Complex Curiosities III",
      "Some like to collect intricate gizmos. You can supply.",
      "",
      "There is a request for /b/Lubricated Bearings/b/.  Friction-free rotors perfect for high-speed rotations.",
      "",
      "Trade those for /b/Ancient Tomes/b/.",
      "",
      "<hr/>",
      "<task task=\"submit_lube_bearing\" quest=\"complex_curiosities_3\"/>",
      "<hr/>",
      "<reward reward=\"award_ancient_tome\" quest=\"complex_curiosities_3\"/>"
    ],
    "groups": {
      "Section C: Challanges": {
        "position": [
          30,
          120
        ]
      }
    },
    "icon": {
      "item": {
        "id": "kubejs:lubricated_bearing",
        "count": 1
      },
      "type": "heracles:item"
    },
    "icon_background": "heracles:textures/gui/quest_backgrounds/default.png",
    "title": {
      "translate": "Complex Curiosities III"
    }
  },
  "settings": {
    "showDependencyArrow": true,
    "repeatable": false,
    "autoClaimRewards": false,
    "individual_progress": false,
    "hidden": "LOCKED",
    "unlockNotification": false
  }
}