{
  "dependencies": [],
  "tasks": {
    "welcome": {
      "type": "heracles:check"
    }
  },
  "rewards": {
    "cmd_plushie": {
      "title": "Plushie!",
      "icon": {
        "item": {
          "id": "plushie_buddies:plushie_fox",
          "count": 1
        },
        "type": "heracles:item"
      },
      "command": "loot give @s loot kubejs:commands/plushies",
      "type": "heracles:command"
    },
    "cmd_sack": {
      "title": "Starting Equipment",
      "icon": {
        "item": {
          "id": "supplementaries:sack",
          "count": 1
        },
        "type": "heracles:item"
      },
      "command": "give @p supplementaries:sack{BlockEntityTag:{ForgeCaps:{},Items:[{Count:1b,Slot:0b,id:\"simpleradio:walkie_talkie\"},{Count:1b,Slot:1b,id:\"farmersdelight:bacon_sandwich\"},{Count:2b,Slot:2b,id:\"farmersdelight:melon_popsicle\"},{Count:1b,Slot:3b,id:\"farmersdelight:apple_cider\"},{Count:1b,Slot:4b,id:\"minecraft:campfire\"},{Count:1b,Slot:5b,id:\"cold_sweat:filled_waterskin\",tag:{temperature:-50}},{Count:1b,Slot:6b,id:\"cold_sweat:filled_waterskin\",tag:{temperature:-50}},{Count:1b,Slot:7b,id:\"cold_sweat:filled_waterskin\",tag:{temperature:50}},{Count:1b,Slot:8b,id:\"cold_sweat:filled_waterskin\",tag:{temperature:50}}]}}",
      "type": "heracles:command"
    }
  },
  "display": {
    "subtitle": {
      "translate": "Welcome"
    },
    "description": [
      "## - Welcome ---",
      "Welcome to Icosahedron, an expert-lite modpack based on combat, tech, and fun systems to master.",
      "",
      "<hint title=\"Note on Skill\" icon=\"minecraft:cobblestone\">",
      "    <p>It's generaly expected that you have played minecraft before, and are fairly good at it. You are not expected to know and have mastered the mods included. This quest book will attempt to guide you through the included mods (and the modifications made to them) as if you've never seen them before.</p>",
      "</hint>",
      "",
      "<details summary=\"An Overview on Changes\">",
      "    <p>Vanilla recipes are mostly untouched, except iron-tier and above armor and tools, which have been modified and can no longer be made normally. Modded recipes have been modified signifigantly. Most recipes have been made more expensive or changed to require other modded processes to be made.</p>",
      "</details>",
      "",
      "This is the quest book. It can be opened with /b/U/b/ (by default) and shows objectives and rewards.",
      "This book will guide you through systems and progression of the mod.",
      "",
      "Some quests may come with handy rewards!",
      "<hr/>",
      "Complete this quest by checking the box.",
      "<task task=\"welcome\" quest=\"Planetfall\"/>",
      "<hr/>",
      "And claim the rewards!",
      "<reward reward=\"cmd_sack\" quest=\"Planetfall\"/>",
      "You should look at the Survival Guide quest next. It'll tell you need-to-know information on how to survive regarding some of the new modded mechanics."
    ],
    "groups": {
      "Section 1: Boots on Ground": {
        "position": [
          0,
          0
        ]
      }
    },
    "icon": {
      "item": {
        "id": "heracles:quest_book",
        "count": 1
      },
      "type": "heracles:item"
    },
    "icon_background": "heracles:textures/gui/quest_backgrounds/diamonds.png",
    "title": {
      "translate": "Planetfall"
    }
  },
  "settings": {
    "showDependencyArrow": true,
    "repeatable": false,
    "autoClaimRewards": false,
    "individual_progress": false,
    "hidden": "LOCKED",
    "unlockNotification": false
  }
}